{
  "id": "rest/reFetch",
  "title": "重新获取 (reFetch)",
  "sidebar_label": "重新获取 (reFetch)",
  "description": "由于 Pea 推崇在组件内维护异步数据，但很多场景中，你需要更新异步数据，比如在 CRUD 功能中，新增、删除、修改、分页、筛选等功能都需要更新异步数据。`@peajs/rest` 提供了三中方式更新数据，三种方式可在不同业务场景中使用，这是`@peajs/rest`的重要功能之一，你应该仔细阅读并理解它的使用场景，使用这种方式管理异步数据，整个应用的状态将变得更加简单，代码量会成本的减少，相应的可维护性大大增加。",
  "source": "@site/docs/rest/refetch.md",
  "permalink": "/docs/rest/reFetch",
  "sidebar": "docs",
  "next": {
    "title": "快速开始",
    "permalink": "/docs/graphql/started"
  },
  "previous": {
    "title": "网络请求 (fetch)",
    "permalink": "/docs/rest/fetch"
  },
  "editUrl": "https://github.com/pea-team/pea/edit/master/website/docs/rest/refetch.md"
}